ressac/ResNetAE_pytorch.py
ressac/Resnet34.py
ressac/__init__.py
ressac/dataset.py
ressac/forebrain.py
ressac/layer.py
ressac/loss.py
ressac/model.py
ressac/plot.py
ressac/specifity.py
ressac/utils.py
ressac-1.0.1.data/scripts/Ressac.py
ressac-1.0.1.dist-info/LICENSE
ressac-1.0.1.dist-info/METADATA
ressac-1.0.1.dist-info/WHEEL
ressac-1.0.1.dist-info/top_level.txt
ressac-1.0.1.dist-info/RECORD
